datatorch/__init__.py
datatorch/agent/__init__.py
datatorch/agent/agent.py
datatorch/agent/client.py
datatorch/agent/directory.py
datatorch/agent/log_handler.py
datatorch/agent/logging.py
datatorch/agent/monitoring.py
datatorch/agent/pipelines/__init__.py
datatorch/agent/pipelines/pipeline.py
datatorch/agent/pipelines/template.py
datatorch/agent/pipelines/action/__init__.py
datatorch/agent/pipelines/action/action.py
datatorch/agent/pipelines/action/cache.py
datatorch/agent/pipelines/action/config.py
datatorch/agent/pipelines/job/__init__.py
datatorch/agent/pipelines/job/job.py
datatorch/agent/pipelines/runner/__init__.py
datatorch/agent/pipelines/runner/command.py
datatorch/agent/pipelines/runner/docker.py
datatorch/agent/pipelines/runner/factory.py
datatorch/agent/pipelines/runner/node.py
datatorch/agent/pipelines/runner/python.py
datatorch/agent/pipelines/runner/runner.py
datatorch/agent/pipelines/runner/shell.py
datatorch/agent/pipelines/step/__init__.py
datatorch/agent/pipelines/step/step.py
datatorch/agent/services/__init__.py
datatorch/agent/utils/__init__.py
datatorch/agent/utils/docker.py
datatorch/agent/utils/process.py
datatorch/api/__init__.py
datatorch/api/api.py
datatorch/api/client.py
datatorch/api/utils.py
datatorch/api/where.py
datatorch/api/entity/__init__.py
datatorch/api/entity/annotation.py
datatorch/api/entity/base.py
datatorch/api/entity/dataset.py
datatorch/api/entity/file.py
datatorch/api/entity/label.py
datatorch/api/entity/project.py
datatorch/api/entity/settings.py
datatorch/api/entity/storage_link.py
datatorch/api/entity/user.py
datatorch/api/entity/sources/__init__.py
datatorch/api/entity/sources/source.py
datatorch/api/entity/sources/image/__init__.py
datatorch/api/entity/sources/image/bounding_box.py
datatorch/api/entity/sources/image/segmentations.py
datatorch/api/entity/sources/image/typings.py
datatorch/api/scripts/__init__.py
datatorch/api/scripts/import_coco.py
datatorch/api/scripts/utils/__init__.py
datatorch-0.4.8.5.dist-info/METADATA
datatorch-0.4.8.5.dist-info/WHEEL
datatorch-0.4.8.5.dist-info/entry_points.txt
datatorch-0.4.8.5.dist-info/top_level.txt
datatorch-0.4.8.5.dist-info/RECORD
