Metadata-Version: 2.2
Name: datatorch
Version: 0.4.8.5
Summary: A CLI and library for interacting with DataTorch.
Home-page: https://github.com/datatorch/python
Author: DataTorch
Author-email: support@datatorch.io
License: MIT license
Classifier: Development Status :: 4 - Beta
Classifier: Environment :: Console
Classifier: Framework :: Pytest
Classifier: Intended Audience :: Developers
Classifier: Natural Language :: English
Classifier: Programming Language :: Python :: 3.9
Classifier: Topic :: Scientific/Engineering :: Artificial Intelligence
Classifier: Topic :: Software Development :: Libraries :: Python Modules
Requires-Python: >=3.9
Requires-Dist: Click==8.0.0
Requires-Dist: gql==3.4.0
Requires-Dist: websockets==10.4
Requires-Dist: websocket-client
Requires-Dist: requests==2.31.0
Requires-Dist: typing_extensions>=4.1.0
Requires-Dist: psutil~=5.9.4
Requires-Dist: aiodocker~=0.19.0
Requires-Dist: Jinja2~=2.0
Requires-Dist: PyYAML~=6.0
Requires-Dist: aiostream~=0.4.0
Requires-Dist: markupsafe==2.0.1
Requires-Dist: requests_toolbelt==0.10.1
Requires-Dist: imantics==0.1.12
Requires-Dist: shapely==2.0.6
Requires-Dist: tqdm~=4.65.0
Requires-Dist: urllib3==1.26.15
Requires-Dist: numpy
Requires-Dist: docker
Requires-Dist: python-magic
Requires-Dist: pycocotools
Dynamic: author
Dynamic: author-email
Dynamic: classifier
Dynamic: description
Dynamic: description-content-type
Dynamic: home-page
Dynamic: license
Dynamic: requires-dist
Dynamic: requires-python
Dynamic: summary
